dataschema/__init__.py
dataschema/_utils.py
dataschema/base.py
dataschema/common.py
dataschema/specs.py
dataschema/utils.py
python_dataschema-0.1.5.dist-info/LICENSE.txt
python_dataschema-0.1.5.dist-info/METADATA
python_dataschema-0.1.5.dist-info/WHEEL
python_dataschema-0.1.5.dist-info/top_level.txt
python_dataschema-0.1.5.dist-info/RECORD
