Metadata-Version: 2.1
Name: python-dataschema
Version: 0.1.5
Summary: DataSchema schema checking for arbitrary data
Home-page: https://github.com/ashafer01/python-dataschema
Author: Alex Shafer
Author-email: ashafer@pm.me
License: MIT
Platform: UNKNOWN
